curlypy/__init__.py
curlypy/__main__.py
curlypy/curlypy.py
curlypy/errors.py
curlypy-0.1.2.dist-info/licenses/LICENSE
curlypy-0.1.2.dist-info/METADATA
curlypy-0.1.2.dist-info/WHEEL
curlypy-0.1.2.dist-info/entry_points.txt
curlypy-0.1.2.dist-info/top_level.txt
curlypy-0.1.2.dist-info/RECORD
