Metadata-Version: 2.4
Name: curlypy
Version: 0.1.2
Summary: A preprocessor to turn python code with braces into python
Author: DevBoiAgru
Project-URL: Homepage, https://github.com/DevBoiAgru/CurlyPy
Project-URL: Issues, https://github.com/DevBoiAgru/CurlyPy/issues
Classifier: Programming Language :: Python :: 3
Classifier: License :: OSI Approved :: MIT License
Classifier: Operating System :: OS Independent
Requires-Python: >=3.8
License-File: LICENSE
Dynamic: license-file
